{
  "day": "Day065",
  "title": "Warranty Pocket Keeper",
  "description": "保証書ポケット is needed when the real decision is small but easy to postpone.",
  "genre": "utility",
  "theme": "Soft",
  "complexity_tier": "small",
  "selected_components": [],
  "complexity_prompt_hint": "Implement the locked brief with one clear hero interaction and keep the main screenshot readable.",
  "story_summary": "家電を買った後、保証書をどこへ置くか決めたい時 / あとで探す物と場所を買った日に固定できる。",
  "tool_name": "Warranty Pocket Keeper",
  "core_action": "block_fill",
  "twist": "散っていた項目が整って少し気持ちいい。",
  "one_sentence": "買った物と保証期限を、あとで探せるポケットにするツール",
  "display_name_ja": "保証書ポケット",
  "purpose_line_ja": "保証書ポケットを作るためのツールです。",
  "use_case_line_ja": "家電を買った後、保証書をどこへ置くか決めたい時に使います。",
  "how_it_works_line_ja": "項目を入れると、結果カードが出ます。",
  "simple_steps_ja": [
    "項目を入れる",
    "追加や編集をする",
    "結果を見る"
  ],
  "one_line_concept": "買った物と保証期限を、あとで探せるポケットにするツール",
  "value_category": "たまに使う実用",
  "target_moment": "家電を買った後、保証書をどこへ置くか決めたい時",
  "user_pain": "保証書、レシート、箱、メール控えが別々になり、壊れた時に探せない。",
  "current_workaround": "レシートを箱に入れる、写真だけ撮る、あとでメール検索に頼る。",
  "why_this_wins": "保管場所と期限と必要書類が一画面で見え、買った直後に置き先が決まる。",
  "primary_payoff": "あとで探す物と場所を買った日に固定できる。",
  "repeat_reason": "家電や大きな買い物の後に毎回使えるから。",
  "first_20_seconds_flow": [
    "品名と購入日を入れる",
    "保証書やレシートの置き場所を追加する",
    "保証ポケットと期限カードが出る"
  ],
  "input_model": "warranty_item_rows",
  "tool_shape": "記録・ログ系",
  "practical_use_requirements": {
    "free_input": true,
    "sample_as_starting_point": true,
    "user_can_add_items": true,
    "user_can_edit_items": true,
    "user_can_delete_items": true,
    "result_changes_with_input": true,
    "fixed_default_choices_only_forbidden": true
  },
  "output_artifact": "保証ポケットと期限カード",
  "empty_state_value": "ドライヤー購入のサンプルから、置き場所と期限をすぐ書き換えられる。",
  "delight_hook": "散っていた項目が整って少し気持ちいい。",
  "share_hook": "準備の結果が一枚で伝わる。。入力した自分の状況が一枚で伝わる。",
  "interaction_hook": "最初の1操作ですぐ結果が見える",
  "capture_hook": "保証ポケットと期限カードが中央に出る画面",
  "media_ready_score": 4,
  "build_to_value_ratio": 5,
  "problem_family": "warranty_deadline_log",
  "input_mode": "receipt_items",
  "interaction_pattern": "block_fill",
  "output_mode": "return_box",
  "visual_shape": "parcel_box",
  "emotional_payoff": "先に決まって楽になる",
  "social_angle": "utility",
  "visual_hook": "保証ポケットと期限カードが中央に出る画面 / 会社ごとの差ではなく、未記載や別料金の行だけが強く浮く比較表の画面",
  "source_batch_id": "batch-065-071",
  "family": "warranty_deadline_log",
  "mechanic": "block_fill",
  "input_style": "receipt_items",
  "output_style": "return_box",
  "output_label": "ここを見ればOKです",
  "audience_promise": "あとで探す物と場所を買った日に固定できる。",
  "publish_hook": "保管場所と期限と必要書類が一画面で見え、買った直後に置き先が決まる。",
  "engine": "brief_driven",
  "interaction_archetype": "block_fill",
  "page_archetype": "parcel_box",
  "ui_variant": "request",
  "intro_variant": "request_frame",
  "interaction_model": "fill_missing_request_blocks",
  "primary_layout": "request_cards_grid",
  "result_presentation_style": "missing_vs_filled_cards",
  "palette_motif": "依頼メモサンド",
  "main_cta": "依頼メモで試す",
  "input_panel_title": "空いている枠を埋める",
  "sample_panel_title": "依頼メモで試す",
  "guide_panel_title": "抜けを減らすコツ",
  "hero_panel_label": "伝わる依頼文",
  "output_shape": "parcel_box",
  "state_model": "block_fill_state",
  "core_loop": "receipt_items -> block_fill -> return_box",
  "component_pack": "parcel_box+return_box",
  "scaffold_id": "brief_canvas",
  "single_shot_text_generator": false,
  "original_twist": "散っていた項目が整って少し気持ちいい。",
  "original_one_sentence": "買った物と保証期限を、あとで探せるポケットにするツール",
  "enhancement_source": "",
  "enhancement_candidate_id": "",
  "enhancement_adopted": false,
  "kill_condition": [
    "入力を変えても結果が変わらない"
  ],
  "plan_scores": {
    "moment_clarity": 5,
    "value_speed": 5,
    "workaround_advantage": 5,
    "output_strength": 5,
    "repeatability": 5,
    "delight_shareability": 5,
    "build_efficiency": 5
  },
  "portfolio_decision": "Pass",
  "biggest_weakness": "batch 内で被りやすい",
  "revision_note": "",
  "revise_priorities": [],
  "adopted_next_batch_complexity": false,
  "adopted_next_batch_components": false,
  "adopted_next_batch_enhancement": false,
  "next_batch_plan_source": "/mnt/c/Users/RYO/dev/ai-dev-exp-control/plans/days/day065.json",
  "next_batch_slot": null,
  "next_batch_recommended_components": [],
  "next_batch_recommended_enhancement": false,
  "keywords": [
    "block_fill",
    "parcel_box",
    "receipt_items",
    "return_box",
    "utility",
    "warranty_deadline_log"
  ],
  "repo_name": "ai-dev-day-065",
  "pages_url": "https://ryo909.github.io/ai-dev-day-065/",
  "youtube_enabled": false
}
